graphkb/__init__.py
graphkb/constants.py
graphkb/genes.py
graphkb/match.py
graphkb/py.typed
graphkb/statement.py
graphkb/types.py
graphkb/util.py
graphkb/vocab.py
tests/__init__.py
tests/data.py
tests/test_genes.py
tests/test_graphkb.py
tests/test_match.py
tests/test_statement.py
tests/test_util.py
tests/test_vocab.py
graphkb-1.15.0.dist-info/LICENSE
graphkb-1.15.0.dist-info/METADATA
graphkb-1.15.0.dist-info/WHEEL
graphkb-1.15.0.dist-info/dependency_links.txt
graphkb-1.15.0.dist-info/top_level.txt
graphkb-1.15.0.dist-info/RECORD
