Metadata-Version: 2.1
Name: graphkb
Version: 1.15.0
Summary: python adapter for interacting with the GraphKB API
Home-page: https://github.com/bcgsc/pori_graphkb_python
Author-email: graphkb@bcgsc.ca
Requires-Python: >=3.6
License-File: LICENSE
Requires-Dist: requests <2.29.0
Requires-Dist: typing-extensions <4.4,>=3.7.4.2
Provides-Extra: deploy
Requires-Dist: twine ; extra == 'deploy'
Requires-Dist: wheel ; extra == 'deploy'
Provides-Extra: dev
Requires-Dist: twine ; extra == 'dev'
Requires-Dist: wheel ; extra == 'dev'
Requires-Dist: pytest ; extra == 'dev'
Requires-Dist: pytest-runner ; extra == 'dev'
Requires-Dist: pytest-cov ; extra == 'dev'
Requires-Dist: mkdocs ; extra == 'dev'
Requires-Dist: markdown-refdocs ; extra == 'dev'
Requires-Dist: mkdocs-material ; extra == 'dev'
Requires-Dist: mkdocs-redirects ; extra == 'dev'
Requires-Dist: black ; extra == 'dev'
Requires-Dist: flake8 ; extra == 'dev'
Requires-Dist: flake8-annotations ; extra == 'dev'
Requires-Dist: isort ; extra == 'dev'
Requires-Dist: mypy ; extra == 'dev'
Provides-Extra: doc
Requires-Dist: mkdocs ; extra == 'doc'
Requires-Dist: markdown-refdocs ; extra == 'doc'
Requires-Dist: mkdocs-material ; extra == 'doc'
Requires-Dist: mkdocs-redirects ; extra == 'doc'
Provides-Extra: test
Requires-Dist: pytest ; extra == 'test'
Requires-Dist: pytest-runner ; extra == 'test'
Requires-Dist: pytest-cov ; extra == 'test'
